quantup_utils/__init__.py
quantup_utils/builtin/__init__.py
quantup_utils/builtin/builtin.py
quantup_utils/builtin/printing.py
quantup_utils/builtin/timer.py
quantup_utils/config/__init__.py
quantup_utils/config/setup.py
quantup_utils/df/__init__.py
quantup_utils/df/helpers.py
quantup_utils/df/summary.py
quantup_utils/plots/__init__.py
quantup_utils/plots/helpers.py
quantup_utils/plots/plot_covariates.py
quantup_utils/plots/plot_factor.py
quantup_utils/plots/plot_numeric.py
quantup_utils/plots/plot_variable.py
quantup_utils/plots/rocs.py
quantup_utils/transformations/__init__.py
quantup_utils/transformations/transformers.py
quantup_utils-1.1.9.dist-info/METADATA
quantup_utils-1.1.9.dist-info/WHEEL
quantup_utils-1.1.9.dist-info/top_level.txt
quantup_utils-1.1.9.dist-info/RECORD
