Metadata-Version: 2.4
Name: quantup_utils
Version: 1.1.9
Summary: Quantup utils mainly for EDA and modelling.
Author: Arkadiusz Kasprzyk
Author-email: arkadiusz.kasprzyk@quantup.pl
Project-URL: Repository, https://github.com/QuantUp/qutils/tree/main/utils-1.0
Project-URL: Bug Reports, https://github.com/QuantUp/qutils/issues/
Keywords: data,plotting,summary,variables,covariates,data frame,EDA,modelling
Classifier: Development Status :: 3 - Alpha
Classifier: Intended Audience :: Developers
Classifier: Topic :: Software Development :: Build Tools
Classifier: License :: OSI Approved :: MIT License
Classifier: Programming Language :: Python :: 3
Classifier: Programming Language :: Python :: 3.7
Classifier: Programming Language :: Python :: 3.8
Classifier: Programming Language :: Python :: 3.9
Classifier: Programming Language :: Python :: 3.10
Classifier: Programming Language :: Python :: 3 :: Only
Requires-Python: >=3.7, <4
Requires-Dist: numpy
Requires-Dist: pandas
Requires-Dist: matplotlib
Requires-Dist: scikit-learn
Requires-Dist: statsmodels
Dynamic: author
Dynamic: author-email
Dynamic: classifier
Dynamic: description
Dynamic: description-content-type
Dynamic: keywords
Dynamic: project-url
Dynamic: requires-dist
Dynamic: requires-python
Dynamic: summary
